README.md
setup.py
gui_fun/__init__.py
gui_fun.egg-info/PKG-INFO
gui_fun.egg-info/SOURCES.txt
gui_fun.egg-info/dependency_links.txt
gui_fun.egg-info/top_level.txt