Metadata-Version: 1.0
Name: gui-fun
Version: 1.0.8
Summary: Create a basic gui for a function
Home-page: http://cct.lsu.edu/~sbrandt/
Author: Steven R. Brandt
Author-email: steven@stevenrbrandt.com
License: LGPL
Platform: UNKNOWN
